CHANGES.txt
MANIFEST.in
README.rst
bootstrap.py
buildout.cfg
setup.py
docs/INSTALL.txt
docs/LICENSE.GPL
docs/LICENSE.txt
ecreall/__init__.py
ecreall.trashcan.egg-info/PKG-INFO
ecreall.trashcan.egg-info/SOURCES.txt
ecreall.trashcan.egg-info/dependency_links.txt
ecreall.trashcan.egg-info/entry_points.txt
ecreall.trashcan.egg-info/namespace_packages.txt
ecreall.trashcan.egg-info/not-zip-safe
ecreall.trashcan.egg-info/requires.txt
ecreall.trashcan.egg-info/top_level.txt
ecreall/trashcan/README.txt
ecreall/trashcan/__init__.py
ecreall/trashcan/api.py
ecreall/trashcan/catalog_monkey.py
ecreall/trashcan/configure.zcml
ecreall/trashcan/etags.py
ecreall/trashcan/events.py
ecreall/trashcan/interfaces.py
ecreall/trashcan/setuphandlers.py
ecreall/trashcan/skins.zcml
ecreall/trashcan/subscribers.zcml
ecreall/trashcan/upgrades.zcml
ecreall/trashcan/utils.py
ecreall/trashcan/viewlets.py
ecreall/trashcan/viewlets.zcml
ecreall/trashcan/locales/ecreall.trashcan.pot
ecreall/trashcan/locales/generate.sh
ecreall/trashcan/locales/plone-manual.pot
ecreall/trashcan/locales/plone.pot
ecreall/trashcan/locales/update.sh
ecreall/trashcan/locales/en/LC_MESSAGES/ecreall.trashcan.mo
ecreall/trashcan/locales/en/LC_MESSAGES/ecreall.trashcan.po
ecreall/trashcan/locales/en/LC_MESSAGES/plone.mo
ecreall/trashcan/locales/en/LC_MESSAGES/plone.po
ecreall/trashcan/locales/es/LC_MESSAGES/ecreall.trashcan.mo
ecreall/trashcan/locales/es/LC_MESSAGES/ecreall.trashcan.po
ecreall/trashcan/locales/es/LC_MESSAGES/plone.mo
ecreall/trashcan/locales/es/LC_MESSAGES/plone.po
ecreall/trashcan/locales/fr/LC_MESSAGES/ecreall.trashcan.mo
ecreall/trashcan/locales/fr/LC_MESSAGES/ecreall.trashcan.po
ecreall/trashcan/locales/fr/LC_MESSAGES/plone.mo
ecreall/trashcan/locales/fr/LC_MESSAGES/plone.po
ecreall/trashcan/profiles/default/actions.xml
ecreall/trashcan/profiles/default/browserlayer.xml
ecreall/trashcan/profiles/default/cssregistry.xml
ecreall/trashcan/profiles/default/metadata.xml
ecreall/trashcan/profiles/default/skins.xml
ecreall/trashcan/profiles/default/trashcan.txt
ecreall/trashcan/profiles/uninstall/actions.xml
ecreall/trashcan/profiles/uninstall/browserlayer.xml
ecreall/trashcan/profiles/uninstall/cssregistry.xml
ecreall/trashcan/profiles/uninstall/metadata.xml
ecreall/trashcan/profiles/uninstall/skins.xml
