Metadata-Version: 1.1
Name: ecreall.trashcan
Version: 1.7.2
Summary: Trashcan for Plone. By Ecreall.
Home-page: http://pypi.python.org/pypi/ecreall.trashcan
Author: Vincent Fretin and Michael Launay
Author-email: development@ecreall.com
License: GPL
Keywords: Trashcan content types Plone Ecreall
Platform: UNKNOWN
Classifier: Development Status :: 3 - Alpha
Classifier: Environment :: Web Environment
Classifier: Framework :: Plone
Classifier: Framework :: Plone :: 4.1
Classifier: Intended Audience :: Developers
Classifier: Intended Audience :: End Users/Desktop
Classifier: Intended Audience :: System Administrators
Classifier: License :: OSI Approved :: GNU General Public License (GPL)
Classifier: Operating System :: OS Independent
Classifier: Programming Language :: Python
Classifier: Programming Language :: Python :: 2.7
Classifier: Topic :: Office/Business :: Groupware
Classifier: Topic :: Office/Business :: Office Suites
Classifier: Topic :: Software Development :: Libraries :: Python Modules
